pyomgclient/__init__.py
pyomgclient/omgclient.py
pyomgclient/utils/__init__.py
pyomgclient/utils/config.py
pyomgclient/utils/generators.py
pyomgclient-1.1.0.dist-info/METADATA
pyomgclient-1.1.0.dist-info/WHEEL
pyomgclient-1.1.0.dist-info/top_level.txt
pyomgclient-1.1.0.dist-info/RECORD
