Metadata-Version: 2.1
Name: pyomgclient
Version: 1.1.0
Summary: a python omegle client
Author: Team XProjects
Keywords: python,omegle,XProjects,TheXProjects,client,omegleclient,pyomgclient,omgclient,pythonomengleclient
Classifier: Development Status :: 2 - Pre-Alpha
Classifier: Intended Audience :: Developers
Classifier: Programming Language :: Python :: 3
Requires-Dist: requests
Requires-Dist: colorama
